filebin/__init__.py
filebin/encoding.py
filebin/main.py
filebin/utils.py
filebin_cli-0.3.2.dist-info/licenses/LICENSE
filebin_cli-0.3.2.dist-info/METADATA
filebin_cli-0.3.2.dist-info/WHEEL
filebin_cli-0.3.2.dist-info/entry_points.txt
filebin_cli-0.3.2.dist-info/top_level.txt
filebin_cli-0.3.2.dist-info/RECORD
