Metadata-Version: 2.4
Name: filebin-cli
Version: 0.3.2
Summary: A cli tool to temporarily share file without any hassle. Uses filebin.net public api
Author-email: "M. Shiraz Kamran" <dev.mshiraz@gmail.com>
Project-URL: Repository, https://github.com/mshirazkamran/filebin-api
Project-URL: Documentation, https://github.com/mshirazkamran/filebin-api?tab=readme-ov-file#-filebin-cli
Keywords: cli,filebin,file-sharing,temporary-files,command line application,click
Classifier: Programming Language :: Python :: 3
Classifier: Programming Language :: Python :: 3.7
Classifier: Programming Language :: Python :: 3.8
Classifier: Programming Language :: Python :: 3.9
Classifier: Programming Language :: Python :: 3.10
Classifier: Programming Language :: Python :: 3.11
Classifier: Programming Language :: Python :: 3.12
Classifier: Operating System :: OS Independent
Classifier: Environment :: Console
Classifier: Topic :: Utilities
Requires-Python: >=3.7.9
License-File: LICENSE
Requires-Dist: click<9.0,>=7.1.2
Requires-Dist: requests<3.0,>=2.25.1
Dynamic: license-file
